cowsay/__init__.py
cowsay/__main__.py
cowsay/characters.py
cowsay/main.py
cowsay/tests/__init__.py
cowsay/tests/solutions.py
cowsay/tests/test_api.py
cowsay/tests/test_output.py
cowsay-6.0.dist-info/LICENSE.txt
cowsay-6.0.dist-info/METADATA
cowsay-6.0.dist-info/WHEEL
cowsay-6.0.dist-info/entry_points.txt
cowsay-6.0.dist-info/top_level.txt
cowsay-6.0.dist-info/RECORD
