Metadata-Version: 2.1
Name: cowsay
Version: 6.0
Summary: The famous cowsay for GNU/Linux is now available for python
Home-page: https://github.com/VaasuDevanS/cowsay-python
Author: Vaasudevan Srinivasan
Author-email: vaasuceg.96@gmail.com
License: GNU-GPL
Classifier: Operating System :: OS Independent
Classifier: Programming Language :: Python :: 3.8
Classifier: Programming Language :: Python :: 3.9
Classifier: Programming Language :: Python :: 3.10
Classifier: Programming Language :: Python :: 3.11
License-File: LICENSE.txt
